LICENSE
MANIFEST.in
README.rst
setup.py
django_right_to_left.egg-info/PKG-INFO
django_right_to_left.egg-info/SOURCES.txt
django_right_to_left.egg-info/dependency_links.txt
django_right_to_left.egg-info/top_level.txt
rtl/__init__.py
rtl/loaders.py