Metadata-Version: 1.0
Name: django-right-to-left
Version: 0.1.1
Summary: A Django template loader that looks for an alternative right to left version of a template file if the activated language is a right to left language such as Arabic or Hebrew.
Home-page: https://github.com/abbas123456/django-right-to-left
Author: Mohammad Abbas
Author-email: mohammad.abbas86@gmail.com
License: BSD
Keywords: Django,translation,internationalization,righ to left,bidi
Platform: UNKNOWN
Classifier: Development Status :: 4 - Beta
Classifier: Environment :: Web Environment
Classifier: Framework :: Django
Classifier: Intended Audience :: Developers
Classifier: License :: OSI Approved :: BSD License
Classifier: Operating System :: OS Independent
Classifier: Programming Language :: Python
